pythondata_cpu_picorv32/__init__.py
pythondata_cpu_picorv32/verilog/.gitignore
pythondata_cpu_picorv32/verilog/COPYING
pythondata_cpu_picorv32/verilog/Makefile
pythondata_cpu_picorv32/verilog/README.md
pythondata_cpu_picorv32/verilog/picorv32.core
pythondata_cpu_picorv32/verilog/picorv32.v
pythondata_cpu_picorv32/verilog/shell.nix
pythondata_cpu_picorv32/verilog/showtrace.py
pythondata_cpu_picorv32/verilog/testbench.cc
pythondata_cpu_picorv32/verilog/testbench.v
pythondata_cpu_picorv32/verilog/testbench_ez.v
pythondata_cpu_picorv32/verilog/testbench_wb.v
pythondata_cpu_picorv32/verilog/.github/workflows/ci.yml
pythondata_cpu_picorv32/verilog/dhrystone/Makefile
pythondata_cpu_picorv32/verilog/dhrystone/README
pythondata_cpu_picorv32/verilog/dhrystone/dhry.h
pythondata_cpu_picorv32/verilog/dhrystone/dhry_1.c
pythondata_cpu_picorv32/verilog/dhrystone/dhry_1_orig.c
pythondata_cpu_picorv32/verilog/dhrystone/dhry_2.c
pythondata_cpu_picorv32/verilog/dhrystone/sections.lds
pythondata_cpu_picorv32/verilog/dhrystone/start.S
pythondata_cpu_picorv32/verilog/dhrystone/stdlib.c
pythondata_cpu_picorv32/verilog/dhrystone/syscalls.c
pythondata_cpu_picorv32/verilog/dhrystone/testbench.v
pythondata_cpu_picorv32/verilog/dhrystone/testbench_nola.v
pythondata_cpu_picorv32/verilog/firmware/README
pythondata_cpu_picorv32/verilog/firmware/custom_ops.S
pythondata_cpu_picorv32/verilog/firmware/firmware.h
pythondata_cpu_picorv32/verilog/firmware/hello.c
pythondata_cpu_picorv32/verilog/firmware/irq.c
pythondata_cpu_picorv32/verilog/firmware/makehex.py
pythondata_cpu_picorv32/verilog/firmware/multest.c
pythondata_cpu_picorv32/verilog/firmware/print.c
pythondata_cpu_picorv32/verilog/firmware/riscv.ld
pythondata_cpu_picorv32/verilog/firmware/riscv.ld.orig
pythondata_cpu_picorv32/verilog/firmware/sections.lds
pythondata_cpu_picorv32/verilog/firmware/sieve.c
pythondata_cpu_picorv32/verilog/firmware/start.S
pythondata_cpu_picorv32/verilog/firmware/stats.c
pythondata_cpu_picorv32-1.0.post218.dist-info/LICENSE
pythondata_cpu_picorv32-1.0.post218.dist-info/METADATA
pythondata_cpu_picorv32-1.0.post218.dist-info/WHEEL
pythondata_cpu_picorv32-1.0.post218.dist-info/top_level.txt
pythondata_cpu_picorv32-1.0.post218.dist-info/RECORD
