Metadata-Version: 2.2
Name: pythondata-cpu-picorv32
Version: 1.0.post218
Summary: Python module containing verilog files for PicoRV32 cpu.
Home-page: https://github.com/litex-hub/pythondata-cpu-picorv32
Author: LiteX Authors
Author-email: litex@googlegroups.com
Project-URL: Bug Tracker, https://github.com/litex-hub/pythondata-cpu-picorv32/issues
Project-URL: Source Code, https://github.com/litex-hub/pythondata-cpu-picorv32
Classifier: Programming Language :: Python :: 3
Classifier: License :: OSI Approved :: ISC License (ISCL)
Classifier: Operating System :: OS Independent
Requires-Python: >=3.5
License-File: LICENSE
Dynamic: author
Dynamic: author-email
Dynamic: classifier
Dynamic: description
Dynamic: description-content-type
Dynamic: home-page
Dynamic: project-url
Dynamic: requires-python
Dynamic: summary
